refidx/__about__.py
refidx/__init__.py
refidx/core.py
refidx/database.npz
refidx/database_nonlinear.npz
refidx-1.3.0.dist-info/licenses/LICENSE.txt
refidx-1.3.0.dist-info/METADATA
refidx-1.3.0.dist-info/WHEEL
refidx-1.3.0.dist-info/top_level.txt
refidx-1.3.0.dist-info/RECORD
