Metadata-Version: 2.4
Name: refidx
Version: 1.3.0
Summary: Refractive index database
Author: Benjamin Vial
Author-email: benjamin.vial84@gmail.com
License-Expression: MIT
Project-URL: homepage, https://benvial.gitlab.io/refidx
Project-URL: code, https://gitlab.com/benvial/refidx
Project-URL: issues, https://gitlab.com/benvial/refidx/issues
Keywords: refractive index,optics,electromagnetics
Classifier: Development Status :: 5 - Production/Stable
Classifier: Intended Audience :: Science/Research
Classifier: Operating System :: OS Independent
Classifier: Programming Language :: Python
Classifier: Programming Language :: Python :: 3
Classifier: Programming Language :: Python :: 3.8
Classifier: Programming Language :: Python :: 3.9
Classifier: Programming Language :: Python :: 3.10
Classifier: Programming Language :: Python :: 3.11
Classifier: Programming Language :: Python :: 3.12
Classifier: Topic :: Scientific/Engineering
Classifier: Topic :: Scientific/Engineering :: Physics
Classifier: Topic :: Scientific/Engineering :: Mathematics
Classifier: Topic :: Utilities
Requires-Python: >=3.10
License-File: LICENSE.txt
Requires-Dist: numpy>=1.20.0
Dynamic: license-file
